scoped/__init__.py
scoped/scope.py
scoped/utils.py
scoped_functions-1.0.0.dist-info/LICENSE
scoped_functions-1.0.0.dist-info/METADATA
scoped_functions-1.0.0.dist-info/WHEEL
scoped_functions-1.0.0.dist-info/top_level.txt
scoped_functions-1.0.0.dist-info/RECORD
