Metadata-Version: 2.1
Name: scoped-functions
Version: 1.0.0
Summary: Utility to run code at function exit
Author: Intel Corporation, CVAT.ai Corporation, Roman Donchenko
Author-email: Maxim Zhiltsov <zhiltsov.max35@gmail.com>
Maintainer-email: Maxim Zhiltsov <zhiltsov.max35@gmail.com>
License: MIT License
Project-URL: repository, https://github.com/zhiltsov-max/scoped
Keywords: context managers,RAII,rollback,cleanup,function exit,object lifetime,utility,library
Classifier: Development Status :: 4 - Beta
Classifier: Operating System :: OS Independent
Classifier: License :: OSI Approved :: MIT License
Classifier: Programming Language :: Python
Requires-Python: >=3.8
License-File: LICENSE
Requires-Dist: attrs (>=21.2)
Provides-Extra: dev
Requires-Dist: black ; extra == 'dev'
Requires-Dist: isort ; extra == 'dev'
